ebthlib
