Metadata-Version: 1.0
Name: ebthlib
Version: 0.2
Summary: w
Home-page: https://github.com/ebth/data-science/tree/master/ebthlib
Author: Matterboy
Author-email: anvesh.gari@ebth.com
License: MIT
Platform: UNKNOWN
